{
    "1": {
        "Name": "Лолита",
        "Heigth": 110,
        "Weight": 90
    },
    "2": {
        "Name": "Семён",
        "Heigth": 150,
        "Weight": 78
    },
    "3": {
        "Name": "Милена",
        "Heigth": 158,
        "Weight": 52
    },
    "4": {
        "Name": "Владимир",
        "Heigth": 160,
        "Weight": 66
    },
    "5": {
        "Name": "Рамзан",
        "Heigth": 180,
        "Weight": 75
    },
    "6": {
        "Name": "Никита",
        "Heigth": 180,
        "Weight": 65
    },
    "7": {
        "Name": "Михаил",
        "Heigth": 187,
        "Weight": 70
    },
    "8": {
        "Name": "Филипп",
        "Heigth": 200,
        "Weight": 100
    },
    "9": {
        "Name": "Снежана",
        "Heigth": 200,
        "Weight": 10
    },
    "10": {
        "Name": "Георгий",
        "Heigth": 220,
        "Weight": 250
    }
}